Workbook

Sheet Sheet1
A1: FORM-3B [See Rule 61(5)]
M2: Year | O2: =Sheet2!Q4 -> 2018-19
M3: Month | O3: =Sheet2!Q5 -> April
A5: 1. | B5: GSTIN | C5: =Sheet2!D7 -> 0 | D5: =Sheet2!E7 -> 0 | E5: =Sheet2!F7 -> 0 | F5: =Sheet2!G7 -> 0 | G5: =Sheet2!H7 -> 0 | H5: =Sheet2!I7 -> 0 | I5: =Sheet2!J7 -> 0 | J5: =Sheet2!K7 -> 0 | ... Q5: =Sheet2!R7 -> 0
A6: 2. | B6: Legal Name | C6: =Sheet2!D8 -> 0
A8: 3.1 | B8: Details of outward supplies and inward supplies liable to reverse charge
A9: Nature of Supplies | C9: Taxable Value | F9: Integrated Tax | I9: Central Tax | L9: State/UT Tax | O9: Cess
A10: 1 | C10: 2 | F10: 3 | I10: 4 | L10: 5 | O10: 6
A11: (a) Outward taxable supplies (other than zero rated, nil rated and exempted) | C11: =Sheet2!D14 -> 0 | F11: =Sheet2!G14 -> 0 | I11: =Sheet2!J14 -> 0 | L11: =Sheet2!M14 -> 0 | O11: =Sheet2!P14 -> 0
A12: (b) Outward taxable supplies (zero rated) | C12: =Sheet2!D15 -> 0 | F12: =Sheet2!G15 -> 0 | I12: =Sheet2!J15 -> 0 | L12: =Sheet2!M15 -> 0 | O12: =Sheet2!P15 -> 0
A13: (c) Other outward supplies (nil rated and exempted) | C13: =Sheet2!D16 -> 0 | F13: =Sheet2!G16 -> 0 | I13: =Sheet2!J16 -> 0 | L13: =Sheet2!M16 -> 0 | O13: =Sheet2!P16 -> 0
A14: (d) Inward supplies liable to reverse charge (other than those covered in 3.1.1) | C14: =Sheet2!D17 -> 0 | F14: =Sheet2!G17 -> 0 | I14: =Sheet2!J17 -> 0 | L14: =Sheet2!M17 -> 0 | O14: =Sheet2!P17 -> 0
A15: (e) Non-GST outward supplies | C15: =Sheet2!D18 -> 0 | F15: =Sheet2!G18 -> 0 | I15: =Sheet2!J18 -> 0 | L15: =Sheet2!M18 -> 0 | O15: =Sheet2!P18 -> 0
A16: Total | C16: =+SUM(C11:E15) -> 0 | F16: =+SUM(F11:H12,F14) -> 0 | I16: =+SUM(I11,I14) -> 0 | L16: =+SUM(L11,L14) -> 0 | O16: =+SUM(O11:Q12,O14) -> 0
A18: 3.1.1 | B18: Details of supplies notified under sub-section (5) of section 9 of the Central Goods and Services Tax Act, 2017 and corresponding provisions in Integrated Goods and Services Tax/Union Territory Goods and Services Tax/State Goods and Services Tax Acts
A19: Nature of Supplies | C19: Taxable Value | F19: Integrated Tax | I19: Central Tax | L19: State/UT Tax | O19: Cess
A20: 1 | C20: 2 | F20: 3 | I20: 4 | L20: 5 | O20: 6
A21: (i) Taxable supplies on which electronic commerce operator pays tax under sub-section (5) of section 9 [to be furnished by the electronic commerce operator]
A22: (ii) Taxable supplies made by the registered person through electronic commerce operator, on which electronic commerce operator is required to pay tax under sub-section (5) of section 9 [to be furnished by person making supplies through electronic commerce operator] | C22: =Sheet2!D19 -> 0 | F22: =Sheet2!G19 -> 0 | I22: =Sheet2!J19 -> 0 | L22: =Sheet2!M19 -> 0 | O22: =Sheet2!P19 -> 0
A24: 3.2 | B24: Of the supplies shown in 3.1(a) and 3.1.1 above, details of inter-state supplies made to unregistered persons, composition taxable persons and UIN holders
A25: Particulars | F25: Place of Supply | J25: Taxable Value | N25: Integrated Tax
A26: 1 | F26: 2 | J26: 3 | N26: 4
A27: Supplies made to Unregistered Persons
A28: Supplies made to Unregistered Persons
A29: Supplies made to Unregistered Persons
A30: Supplies made to Unregistered Persons
A31: Supplies made to Unregistered Persons
A32: Supplies made to Unregistered Persons
A33: Supplies made to Unregistered Persons
A34: Supplies made to Unregistered Persons
A35: Supplies made to Unregistered Persons
A36: Supplies made to Unregistered Persons
A37: Supplies made to Unregistered Persons
A38: Supplies made to Unregistered Persons
... A57: Supplies made to UIN Holders
A58: 4. | B58: Eligible Input Tax Credit
A59: Details | F59: Integrated Tax | I59: Central Tax | L59: State/UT Tax | O59: Cess
A60: 1 | F60: 2 | I60: 3 | L60: 4 | O60: 5
A61: (A) ITC Available (whether in full or in part)
A62: (1) Import of goods | F62: =Sheet2!D45 -> 0 | I62: =Sheet2!H45 -> 0 | L62: =Sheet2!L45 -> 0 | O62: =Sheet2!P45 -> 0
A63: (2) Import of services | F63: =Sheet2!D46 -> 0 | I63: =Sheet2!H46 -> 0 | L63: =Sheet2!L46 -> 0 | O63: =Sheet2!P46 -> 0
A64: (3) Inward supplies liable to reverse charge (other than 1 & 2) | F64: =Sheet2!D47 -> 0 | I64: =Sheet2!H47 -> 0 | L64: =Sheet2!L47 -> 0 | O64: =Sheet2!P47 -> 0
A65: (4) Inward supplies from ISD | F65: =Sheet2!D49 -> 0 | I65: =Sheet2!H49 -> 0 | L65: =Sheet2!L49 -> 0 | O65: =Sheet2!P49 -> 0
A66: (5) All other ITC | F66: =Sheet2!D50+Sheet2!D55 -> 0 | I66: =Sheet2!H50+Sheet2!H55 -> 0 | L66: =Sheet2!L50+Sheet2!L55 -> 0 | O66: =Sheet2!P50+Sheet2!P55 -> 0
A67: Total (A) | F67: =+SUM(F62:H66) -> 0 | I67: =+SUM(I62:K66) -> 0 | L67: =+SUM(L62:N66) -> 0 | O67: =+SUM(O62:Q66) -> 0
A68: (B) ITC Reversed
A69: (1) As per rules 38, 42 and 43 of CGST Rules and section 17(5) | F69: =Sheet2!D52+Sheet2!D56+Sheet2!D55 -> 0 | I69: =Sheet2!H52+Sheet2!H56+Sheet2!H55 -> 0 | L69: =Sheet2!L52+Sheet2!L56+Sheet2!L55 -> 0 | O69: =Sheet2!P52+Sheet2!P56+Sheet2!P55 -> 0
A70: (2) Others | F70: =Sheet2!D53 -> 0 | I70: =Sheet2!H53 -> 0 | L70: =Sheet2!L53 -> 0 | O70: =Sheet2!P53 -> 0 | R70: =Sheet2!S53 -> 0 | S70: =Sheet2!T53 -> 0 | T70: =Sheet2!U53 -> 0 | U70: =Sheet2!V53 -> 0
A71: Total (B) | F71: =+SUM(F69:H70) -> 0 | I71: =+SUM(I69:K70) -> 0 | L71: =+SUM(L69:N70) -> 0 | O71: =+SUM(O69:Q70) -> 0
A72: (C) Net ITC Available [(A) - (B)] | F72: =+F67-F71 -> 0 | I72: =+I67-I71 -> 0 | L72: =+L67-L71 -> 0 | O72: =+O67-O71 -> 0
A73: (D) Other Details
A74: (1) ITC reclaimed which was reversed under Table 4(B)(2) in earlier tax period | F74: 0 | I74: 0 | L74: 0 | O74: 0
A75: (2) Ineligible ITC under section 16(4) and ITC restricted due to PoS provisions | F75: 0 | I75: 0 | L75: 0 | O75: 0
A76: Total (D) | F76: =+SUM(F74:H75) -> 0 | I76: =+SUM(I74:K75) -> 0 | L76: =+SUM(L74:N75) -> 0 | O76: =+SUM(O74:Q75) -> 0
A78: 5. | B78: Values of exempt, nil-rated and non-GST inward supplies
A79: Nature of Supplies | H79: Inter-State Supplies | M79: Intra-State Supplies
A80: 1 | H80: 2 | M80: 3
A81: From a supplier under composition scheme, exempt and nil rated supply | H81: =Sheet2!E63 -> 0 | M81: =Sheet2!L63 -> 0
A82: Non-GST supply | H82: =Sheet2!E64 -> 0 | M82: =Sheet2!L64 -> 0
A84: Particulars | F84: Integrated Tax | I84: Central Tax | L84: State/UT Tax | O84: Cess
A85: Opening Balance | F85: =Sheet2!D40 -> 0 | I85: =Sheet2!H40 -> 0 | L85: =Sheet2!L40 -> 0 | O85: =Sheet2!P40 -> 0
A87: 6.1 | B87: Payment of Tax
A88: Description | F88: Tax Payable | H88: Paid Through ITC | P88: Payable in Cash
H89: Integrated Tax | J89: Central Tax | L89: State/UT Tax | N89: Cess
A90: 1 | F90: 2 | H90: 3 | J90: 4 | L90: 5 | N90: 6 | P90: 7
A91: (A) Forward Charge
A92: Integrated Tax | F92: =Sheet2!D71 -> 0 | H92: =Sheet2!F71 -> 0 | J92: =Sheet2!H71 -> 0 | L92: =Sheet2!J71 -> 0 | N92: =Sheet2!L71 -> 0 | P92: =+F92-H92-J92-L92 -> 0
A93: Central Tax | F93: =Sheet2!D72 -> 0 | H93: =Sheet2!F72 -> 0 | J93: =Sheet2!H72 -> 0 | L93: =Sheet2!J72 -> 0 | N93: =Sheet2!L72 -> 0 | P93: =+F93-H93-J93 -> 0
A94: State/UT Tax | F94: =Sheet2!D73 -> 0 | H94: =Sheet2!F73 -> 0 | J94: =Sheet2!H73 -> 0 | L94: =Sheet2!J73 -> 0 | N94: =Sheet2!L73 -> 0 | P94: =+F94-H94-L94 -> 0
A95: Cess | F95: =Sheet2!D74 -> 0 | H95: =Sheet2!F74 -> 0 | J95: =Sheet2!H74 -> 0 | L95: =Sheet2!J74 -> 0 | N95: =Sheet2!L74 -> 0 | P95: =+F95-N95 -> 0
A96: Total | F96: =+SUM(F92:G95) -> 0 | H96: =+SUM(H92:I94) -> 0 | J96: =+SUM(J92:K93) -> 0 | L96: =+SUM(L94,L92) -> 0 | N96: =+N95 -> 0 | P96: =+SUM(P92:Q95) -> 0
A97: (B) Reverse Charge
A98: Integrated Tax | F98: =Sheet2!D75 -> 0 | H98: =Sheet2!F75 -> 0 | J98: =Sheet2!H75 -> 0 | L98: =Sheet2!J75 -> 0 | N98: =Sheet2!L75 -> 0 | P98: =+F98 -> 0
A99: Central Tax | F99: =Sheet2!D76 -> 0 | H99: =Sheet2!F76 -> 0 | J99: =Sheet2!H76 -> 0 | L99: =Sheet2!J76 -> 0 | N99: =Sheet2!L76 -> 0 | P99: =+F99 -> 0
A100: State/UT Tax | F100: =Sheet2!D77 -> 0 | H100: =Sheet2!F77 -> 0 | J100: =Sheet2!H77 -> 0 | L100: =Sheet2!J77 -> 0 | N100: =Sheet2!L77 -> 0 | P100: =+F100 -> 0
A101: Cess | P101: =+F101 -> 0
A102: Total [(A) + (B)] | F102: =SUM(F98:G101) -> 0 | H102: 0 | J102: 0 | L102: 0 | N102: 0 | P102: =SUM(P98:Q101) -> 0
A103: Grand Total | F103: =+F102+F96 -> 0 | H103: =+H102+H96 -> 0 | J103: =+J102+J96 -> 0 | L103: =+L102+L96 -> 0 | N103: =+N102+N96 -> 0 | P103: =+P102+P96 -> 0
A105: 6.2 | B105: TDS/TCS Credit
A106: Details | F106: Integrated Tax | J106: Central Tax | N106: State/UT Tax
A107: 1 | F107: 2 | J107: 3 | N107: 4
A108: TDS
A109: TCS
A110: Total | F110: =+SUM(F108:I109) -> 0 | J110: =+SUM(J108:M109) -> 0 | N110: =+SUM(N108:Q109) -> 0
A111: Balance After Adjustments
B112: =Sheet2!C81 -> Integrated Tax | C112: =Sheet2!D81 -> 0
B113: =Sheet2!C82 -> Central Tax | C113: =Sheet2!D82 -> 0
B114: =Sheet2!C83 -> State/UT Tax | C114: =Sheet2!D83 -> 0
B115: =Sheet2!C84 -> Cess | C115: =Sheet2!D84 -> 0
A117: Verification (by Authorized Signatory)
A118: I hereby solemnly affirm and declare that the information given herein above is true and correct to the best of my knowledge and belief and nothing has been concealed therefrom.
A120: Instructions:
A121: 1) Value of Taxable Supplies = Value of invoices + value of Debit Notes – value of credit notes + value of advances received for which invoices have not been issued in the same month – value of advances adjusted against invoices.
A122: 2) Details of advances as well as adjustment of same against invoices to be adjusted and not shown separately.
A123: 3) Amendment in any details to be adjusted and not shown separately.
A124: 4) An Electronic Commerce Operator (ECO) shall not include in 3.1(a) above, the supplies on which the ECO is required to pay tax under sub-section (5) of section 9 of the Central Goods and Services Tax Act, 2017 and shall report such supplies in 3.1.1(i) above.
A125: 5) A registered person making supplies through an Electronic Commerce Operator (ECO) shall not include in 3.1(a) above, the supplies on which the ECO is required to pay tax under sub-section (5) of section 9 of the Central Goods and Services Tax Act, 2017 and shall report such supplies in 3.1.1(ii) above.

Sheet Sheet2
B1: Form GSTR-3B
B2: [ See Rule 61(5) ]
O4: Year | Q4: 2018-19
O5: Month | Q5: April
B7: 1 | C7: GSTIN
B8: 2 | C8: Legal name of the registered person
B10: 3.1 | C10: Detail of Outward Supplies and Inward supplies liable to reverse charges
C12: Nature of Supplies | D12: Total Taxable Value | G12: Integrated Tax | J12: Central Tax | M12: State/ UT Tax | P12: Cess
C13: 1 | D13: 2 | G13: 3 | J13: 4 | M13: 5 | P13: 6
C14: ( a) Outward taxable supplies (other than zero rated, nil rated and exempted) | G14: 0 | J14: 0 | M14: 0 | P14: 0
C15: ( b) Outward taxable supplies (zero rated) | G15: 0 | J15: 0 | M15: 0 | P15: 0
C16: ( c) Other outward supplies, (Nil rated, exempted) | G16: 0 | J16: 0 | M16: 0 | P16: 0
C17: ( d) Inward supplies (liable to reverse charge) | G17: 0 | J17: 0 | M17: 0 | P17: 0
C18: ( e) Non GST outward supplies
C19: ( f) Supplies U/S 9(5) | G19: 0 | J19: 0 | M19: 0 | P19: 0
B21: 3.2 | C21: 3.2 Of the supplies shown in 3.1 (a) above, details of inter-State supplies made to unregistered persons,
C22: composition taxable persons and UIN holders
D24: Place of Supply (State/UT) | I24: Total Taxable Value | N24: Amount of Integrated Tax
C25: 1 | D25: 2 | I25: 3 | N25: 4
C26: Supplies made to Unregistered Persons
C27: Supplies made to Unregistered Persons
C28: Supplies made to Unregistered Persons
C29: Supplies made to Unregistered Persons
C30: Supplies made to Unregistered Persons
C31: Supplies made to Unregistered Persons
C32: Supplies made to Composition Taxable Persons
C33: Supplies made to Composition Taxable Persons
C34: Supplies made to Composition Taxable Persons
C35: Supplies made to Composition Taxable Persons
C36: Supplies made to Composition Taxable Persons
C37: Supplies made to Composition Taxable Persons
C38: Supplies made to UIN Holders
C40: Opening Balance | D40: 0 | H40: 0 | L40: 0 | P40: 0
B41: 4 | C41: Eligible ITC
C42: Details | D42: Integrated Tax | H42: Central Tax | L42: State/ UT Tax | P42: Cess
C43: 1 | D43: 2 | H43: 3 | L43: 4 | P43: 5
C44: (A) ITC Available (whether in full or part)
C45: (1) Import of goods | D45: 0 | P45: 0
C46: (2) Import of services | D46: 0 | P46: 0
C47: (3) Inward supplies liable to reverse charge (other | D47: 0
C48: than 1 & 2 above) | D48: 0
C49: (4) Inward supplies from ISD | D49: 0
C50: (5) All other ITC | D50: =D44-(D45+D46+D47+D48+D49) -> 0 | H50: =H44-(H45+H46+H47+H48+H49) -> 0 | L50: =L44-(L45+L46+L47+L48+L49) -> 0 | P50: =P44-(P45+P46+P47+P48+P49) -> 0
C51: (B) ITC Reversed | D51: =D52+D53 -> 0 | H51: =H52+H53 -> 0 | L51: =L52+L53 -> 0 | P51: =P52+P53 -> 0
C52: (1) As per rules 42 & 43 of CGST Rules | D52: 0
C53: (2) Others | D53: 0 | H53: 0 | L53: 0 | P53: 0
C54: (C) Net ITC Available (A) – (B) | D54: =(D45+D46+D47+D48+D49+D50)-D51 -> 0 | H54: =(H45+H46+H47+H48+H49+H50)-H51 -> 0 | L54: =(L45+L46+L47+L48+L49+L50)-L51 -> 0 | P54: =(P45+P46+P47+P48+P49+P50)-P51 -> 0
C55: (D) Ineligible ITC
C56: (1) As per section 17(5) | D56: 0
C57: (2) Others
B59: 5 | C59: Values of exempt, nil-rated and non-GST inward supplies
C61: Nature of supplies | E61: Inter-State supplies | L61: Intra-State supplies
C62: 1 | E62: 2 | L62: 3
C63: From a supplier under composition scheme, Exempt and Nil rated supply
C64: Non GST supply
B66: 6.1 | C66: Payment of Tax
C68: Description | D68: Tax payable | F68: Paid through ITC | N68: Tax Paid TDS/TCS | O68: Tax/Cess paid in cash | Q68: Interest | R68: Late Fee
F69: Integrated Tax | H69: Central Tax | J69: State/UT tax | L69: Cess
C70: 1 | D70: 2 | F70: 3 | H70: 4 | J70: 5 | L70: 6 | N70: 7 | O70: 8 | Q70: 9 | R70: 10
C71: Integrated Tax | D71: =G14+G15+G16 -> 0 | F71: 0 | H71: 0 | J71: 0 | L71: 0 | O71: =D71-(F71+H71+J71) -> 0
C72: Central Tax | D72: =J14+J15+J16 -> 0 | F72: 0 | H72: 0 | L72: 0 | O72: =D72-(F72+H72+J72) -> 0
C73: State/UT Tax | D73: =M14+M15+M16 -> 0 | F73: 0 | J73: =L54 -> 0 | L73: 0 | O73: =D73-(F73+H73+J73) -> 0
C74: Cess | D74: =P14+P15+P16+P17 -> 0 | L74: =P54 -> 0 | O74: =D74-(F74+H74+J74+L74) -> 0
C75: Inward Charges ( Integrated Tax ) | D75: =G17 -> 0 | L75: =P55 -> 0 | O75: =D75 -> 0
C76: Inward Charges ( Central Tax ) | D76: =J17 -> 0 | L76: =P56 -> 0 | O76: =D76 -> 0
C77: Inward Charges ( State / UT Tax ) | D77: =M17 -> 0 | L77: =P57 -> 0 | O77: =D77 -> 0
C79: BALANCE AFTER ADJUSTMENTS
C81: Integrated Tax | D81: 0
C82: Central Tax | D82: 0
C83: State/UT Tax | D83: 0
C84: Cess | D84: =(P40+P54)-D74 -> 0
B86: 6.2 | C86: TDS/TCS Credit
C88: Details | D88: Integrated Tax | I88: Central Tax | N88: State/ UT Tax
C89: 1 | D89: 2 | I89: 3 | N89: 4
C90: TDS
C91: TCS
C93: Verification (by Authorised signatory)
C95: I hereby solemnly affirm and declare that the information given herein above is true and correct to the best of my knowledge and belief
C96: and nothing has been concealed there from.
C98: Instructions:
C99: 1) Value of Taxable Supplies = Value of invoices + value of Debit Notes – value of credit notes + value of advances received for which
C100: invoices have not been issued in the same month – value of advances adjusted against invoices
C102: 2) Details of advances as well as adjustment of same against invoices to be adjusted and not shown separately
C104: 3) Amendment in any details to be adjusted and not shown separately.

Sheet Sale
E1: =SUBTOTAL(9,E3:E5000) -> 0 | G1: =SUBTOTAL(9,G3:G5000) -> 0 | H1: =SUBTOTAL(9,H3:H5000) -> 0 | I1: =SUBTOTAL(9,I3:I5000) -> 0 | J1: =SUBTOTAL(9,J3:J5000) -> 0
A2: Account Name | B2: GST No. | C2: Bill No. | D2: Date | E2: Taxable Value | F2: Gst Rate | G2: C.Gst | H2: S.Gst | I2: I.Gst | J2: Cess | K2: Sheet2 Col.No.

Sheet Purchase
E1: =SUBTOTAL(9,E3:E5000) -> 0 | G1: =SUBTOTAL(9,G3:G5000) -> 0 | H1: =SUBTOTAL(9,H3:H5000) -> 0 | I1: =SUBTOTAL(9,I3:I5000) -> 0 | J1: =SUBTOTAL(9,J3:J5000) -> 0
A2: Account Name | B2: GST No. | C2: Bill No. | D2: Input Date | E2: Taxable Value | F2: Gst Rate | G2: C.Gst | H2: S.Gst | I2: I.Gst | J2: Cess | K2: Sheet2 Col.No. | L2: Vch. Date

Sheet Other
E1: =SUBTOTAL(9,E3:E5000) -> 0 | G1: =SUBTOTAL(9,G3:G5000) -> 0 | H1: =SUBTOTAL(9,H3:H5000) -> 0 | I1: =SUBTOTAL(9,I3:I5000) -> 0 | J1: =SUBTOTAL(9,J3:J5000) -> 0
A2: Account Name | B2: State Name | C2: Bill No. | D2: Date | E2: Taxable Value | F2: Gst Rate | G2: C.Gst | H2: S.Gst | I2: I.Gst | J2: Cess | K2: Tax Type
